PyCSP/Functions.py
PyCSP/GScheme.py
PyCSP/Simplify.py
PyCSP/Solver.py
PyCSP/ThermoKinetics.py
PyCSP/profiling_tools.py
PyCSP/soln2ck.py
PyCSP/soln2cti.py
PyCSP/utils.py
pycsp_lib-1.4.0.post2.dist-info/licenses/LICENSE
pycsp_lib-1.4.0.post2.dist-info/METADATA
pycsp_lib-1.4.0.post2.dist-info/WHEEL
pycsp_lib-1.4.0.post2.dist-info/top_level.txt
pycsp_lib-1.4.0.post2.dist-info/RECORD
