Metadata-Version: 2.4
Name: PyCSP-lib
Version: 1.4.0.post2
Summary: A collection of tools for the Computational Singular Perturbation analysis of chemically reacting flows
Home-page: https://github.com/rmalpica/PyCSP
Author: Riccardo Malpica Galassi
Author-email: Riccardo Malpica Galassi <riccardo.malpicagalassi@uniroma1.it>
License-Expression: MIT
Project-URL: Homepage, https://github.com/rmalpica/PyCSP
Classifier: Programming Language :: Python :: 3
Classifier: Operating System :: OS Independent
Requires-Python: >=3
License-File: LICENSE
Requires-Dist: numpy
Requires-Dist: matplotlib
Requires-Dist: cantera>=3.0.0
Requires-Dist: pandas
Dynamic: author
Dynamic: home-page
Dynamic: license-file
Dynamic: requires-python
